alexa_responses/__init__.py
alexa_responses/alexa_responses.py
alexa_responses/alexa_smarthome.py
alexa_responses-0.0.3.dist-info/LICENSE
alexa_responses-0.0.3.dist-info/METADATA
alexa_responses-0.0.3.dist-info/WHEEL
alexa_responses-0.0.3.dist-info/top_level.txt
alexa_responses-0.0.3.dist-info/RECORD
