Metadata-Version: 2.1
Name: alexa-responses
Version: 0.0.3
Summary: Alexa responses python module
Home-page: https://github.com/earada/alexa-responses
Author: Eduardo Arada
Author-email: eduardo.arada@gmail.com
License: UNKNOWN
Platform: UNKNOWN
Classifier: Programming Language :: Python :: 3
Classifier: License :: OSI Approved :: MIT License
Classifier: Operating System :: OS Independent
Requires-Python: >=3.6
